lemonsqueezy/__init__.py
lemonsqueezy/client.py
lemonsqueezy/protocols.py
lemonsqueezy/api/__init__.py
lemonsqueezy/api/checkout.py
lemonsqueezy/api/customer.py
lemonsqueezy/api/discount.py
lemonsqueezy/api/discount_redemption.py
lemonsqueezy/api/errors.py
lemonsqueezy/api/file.py
lemonsqueezy/api/license_api.py
lemonsqueezy/api/license_key_instances.py
lemonsqueezy/api/license_keys.py
lemonsqueezy/api/order.py
lemonsqueezy/api/prices.py
lemonsqueezy/api/product.py
lemonsqueezy/api/store.py
lemonsqueezy/api/subscription.py
lemonsqueezy/api/subscription_invoices.py
lemonsqueezy/api/subscription_items.py
lemonsqueezy/api/user.py
lemonsqueezy/api/variant.py
lemonsqueezy/models/__init__.py
lemonsqueezy/models/checkout.py
lemonsqueezy/models/customer.py
lemonsqueezy/models/discount.py
lemonsqueezy/models/discount_redemption.py
lemonsqueezy/models/file.py
lemonsqueezy/models/license_api.py
lemonsqueezy/models/license_key.py
lemonsqueezy/models/license_key_instance.py
lemonsqueezy/models/order.py
lemonsqueezy/models/prices.py
lemonsqueezy/models/product.py
lemonsqueezy/models/store.py
lemonsqueezy/models/subscription.py
lemonsqueezy/models/subscription_invoice.py
lemonsqueezy/models/subscription_item.py
lemonsqueezy/models/user.py
lemonsqueezy/models/variant.py
lemonsqueezy-0.2.0.dist-info/METADATA
lemonsqueezy-0.2.0.dist-info/WHEEL
lemonsqueezy-0.2.0.dist-info/licenses/LICENSE
lemonsqueezy-0.2.0.dist-info/RECORD
