Metadata-Version: 2.4
Name: lemonsqueezy
Version: 0.2.0
Summary: LemonSqueezy-py-api is an unofficial Python library for interacting with the LemonSqueezy API.
License-File: LICENSE
Requires-Python: >=3.10
Requires-Dist: pydantic-settings>=2.6.1
Requires-Dist: pydantic>=2.9.2
Requires-Dist: requests>=2.32.3
